{
  "timestamp": "2025-07-27T02:01:52.606663",
  "data_summary": {
    "total_spend": 802346.97,
    "total_revenue": 2755770.0979,
    "total_impressions": 648,
    "total_clicks": 0,
    "overall_roas": 3.4346363866744585,
    "overall_ctr": 0.0,
    "platform_count": 6,
    "campaign_count": 4
  },
  "platforms": [
    {
      "platform": "Meta",
      "spend": 231217.88,
      "revenue": 703366.8404999999,
      "impressions": 230,
      "clicks": 0,
      "conversions": 0,
      "roas": 2.9525,
      "ctr": 0.0
    },
    {
      "platform": "Dv360",
      "spend": 190032.24999999997,
      "revenue": 701471.8026,
      "impressions": 115,
      "clicks": 0,
      "conversions": 0,
      "roas": 3.4785555555555554,
      "ctr": 0.0
    },
    {
      "platform": "Amazon",
      "spend": 98869.02000000005,
      "revenue": 368174.18509999994,
      "impressions": 26,
      "clicks": 0,
      "conversions": 0,
      "roas": 3.577833333333333,
      "ctr": 0.0
    },
    {
      "platform": "Cm360",
      "spend": 153267.81000000006,
      "revenue": 506998.7581,
      "impressions": 192,
      "clicks": 0,
      "conversions": 0,
      "roas": 2.985,
      "ctr": 0.0
    },
    {
      "platform": "Sa360",
      "spend": 99916.43,
      "revenue": 405246.1998,
      "impressions": 52,
      "clicks": 0,
      "conversions": 0,
      "roas": 4.080333333333333,
      "ctr": 0.0
    },
    {
      "platform": "Tradedesk",
      "spend": 29043.579999999994,
      "revenue": 70512.31180000001,
      "impressions": 33,
      "clicks": 0,
      "conversions": 0,
      "roas": 2.503333333333333,
      "ctr": 0.0
    }
  ],
  "campaigns": [
    {
      "campaign": "FreshNest Summer Grilling",
      "spend": 178791.87999999998,
      "revenue": 585391.4675999999,
      "impressions": 115,
      "clicks": 0,
      "conversions": 0,
      "roas": 3.2592222222222222,
      "ctr": 0.0
    },
    {
      "campaign": "FreshNest Back to School",
      "spend": 376294.7299999999,
      "revenue": 1420931.4308999996,
      "impressions": 338,
      "clicks": 0,
      "conversions": 0,
      "roas": 3.6734999999999998,
      "ctr": 0.0
    },
    {
      "campaign": "FreshNest Holiday Recipes",
      "spend": 98284.97000000006,
      "revenue": 277439.62429999997,
      "impressions": 66,
      "clicks": 0,
      "conversions": 0,
      "roas": 2.778777777777778,
      "ctr": 0.0
    },
    {
      "campaign": "FreshNest Pantry Staples",
      "spend": 148975.39000000007,
      "revenue": 472007.5750999999,
      "impressions": 129,
      "clicks": 0,
      "conversions": 0,
      "roas": 3.0490000000000004,
      "ctr": 0.0
    }
  ],
  "test_questions": [
    {
      "question": "How much money did we spend?",
      "expected": 802346.97,
      "category": "basic_metrics"
    },
    {
      "question": "How much revenue did we generate?",
      "expected": 2755770.0979,
      "category": "basic_metrics"
    },
    {
      "question": "How many impressions did we get?",
      "expected": 648,
      "category": "basic_metrics"
    },
    {
      "question": "How many clicks did we get?",
      "expected": 0,
      "category": "basic_metrics"
    },
    {
      "question": "What is our average ROAS?",
      "expected": 3.4346363866744585,
      "category": "basic_metrics"
    },
    {
      "question": "What is our overall CTR?",
      "expected": 0.0,
      "category": "basic_metrics"
    },
    {
      "question": "How many platforms do we have?",
      "expected": 6,
      "category": "platform_analysis"
    },
    {
      "question": "Which platform performed best?",
      "expected": 4.080333333333333,
      "category": "platform_analysis"
    },
    {
      "question": "Which platform spent the most?",
      "expected": 231217.88,
      "category": "platform_analysis"
    },
    {
      "question": "How much did we spend on Meta?",
      "expected": 231217.88,
      "category": "platform_specific"
    },
    {
      "question": "What is the ROAS for Meta?",
      "expected": 2.9525,
      "category": "platform_specific"
    },
    {
      "question": "How much did we spend on Dv360?",
      "expected": 190032.24999999997,
      "category": "platform_specific"
    },
    {
      "question": "What is the ROAS for Dv360?",
      "expected": 3.4785555555555554,
      "category": "platform_specific"
    },
    {
      "question": "How much did we spend on Amazon?",
      "expected": 98869.02000000005,
      "category": "platform_specific"
    },
    {
      "question": "What is the ROAS for Amazon?",
      "expected": 3.577833333333333,
      "category": "platform_specific"
    },
    {
      "question": "How much did we spend on Cm360?",
      "expected": 153267.81000000006,
      "category": "platform_specific"
    },
    {
      "question": "What is the ROAS for Cm360?",
      "expected": 2.985,
      "category": "platform_specific"
    },
    {
      "question": "How much did we spend on Sa360?",
      "expected": 99916.43,
      "category": "platform_specific"
    },
    {
      "question": "What is the ROAS for Sa360?",
      "expected": 4.080333333333333,
      "category": "platform_specific"
    },
    {
      "question": "How much did we spend on Tradedesk?",
      "expected": 29043.579999999994,
      "category": "platform_specific"
    },
    {
      "question": "What is the ROAS for Tradedesk?",
      "expected": 2.503333333333333,
      "category": "platform_specific"
    },
    {
      "question": "Which campaign performed best?",
      "expected": 3.6734999999999998,
      "category": "campaign_analysis"
    },
    {
      "question": "What did we learn from this campaign?",
      "expected": "insights",
      "category": "advanced_analysis"
    },
    {
      "question": "How can I optimize my campaigns?",
      "expected": "recommendations",
      "category": "advanced_analysis"
    },
    {
      "question": "What is our campaign summary?",
      "expected": "summary",
      "category": "advanced_analysis"
    }
  ],
  "categories": {
    "basic_metrics": [
      {
        "question": "How much money did we spend?",
        "expected": 802346.97,
        "category": "basic_metrics"
      },
      {
        "question": "How much revenue did we generate?",
        "expected": 2755770.0979,
        "category": "basic_metrics"
      },
      {
        "question": "How many impressions did we get?",
        "expected": 648,
        "category": "basic_metrics"
      },
      {
        "question": "How many clicks did we get?",
        "expected": 0,
        "category": "basic_metrics"
      },
      {
        "question": "What is our average ROAS?",
        "expected": 3.4346363866744585,
        "category": "basic_metrics"
      },
      {
        "question": "What is our overall CTR?",
        "expected": 0.0,
        "category": "basic_metrics"
      }
    ],
    "platform_analysis": [
      {
        "question": "How many platforms do we have?",
        "expected": 6,
        "category": "platform_analysis"
      },
      {
        "question": "Which platform performed best?",
        "expected": 4.080333333333333,
        "category": "platform_analysis"
      },
      {
        "question": "Which platform spent the most?",
        "expected": 231217.88,
        "category": "platform_analysis"
      }
    ],
    "platform_specific": [
      {
        "question": "How much did we spend on Meta?",
        "expected": 231217.88,
        "category": "platform_specific"
      },
      {
        "question": "What is the ROAS for Meta?",
        "expected": 2.9525,
        "category": "platform_specific"
      },
      {
        "question": "How much did we spend on Dv360?",
        "expected": 190032.24999999997,
        "category": "platform_specific"
      },
      {
        "question": "What is the ROAS for Dv360?",
        "expected": 3.4785555555555554,
        "category": "platform_specific"
      },
      {
        "question": "How much did we spend on Amazon?",
        "expected": 98869.02000000005,
        "category": "platform_specific"
      },
      {
        "question": "What is the ROAS for Amazon?",
        "expected": 3.577833333333333,
        "category": "platform_specific"
      },
      {
        "question": "How much did we spend on Cm360?",
        "expected": 153267.81000000006,
        "category": "platform_specific"
      },
      {
        "question": "What is the ROAS for Cm360?",
        "expected": 2.985,
        "category": "platform_specific"
      },
      {
        "question": "How much did we spend on Sa360?",
        "expected": 99916.43,
        "category": "platform_specific"
      },
      {
        "question": "What is the ROAS for Sa360?",
        "expected": 4.080333333333333,
        "category": "platform_specific"
      },
      {
        "question": "How much did we spend on Tradedesk?",
        "expected": 29043.579999999994,
        "category": "platform_specific"
      },
      {
        "question": "What is the ROAS for Tradedesk?",
        "expected": 2.503333333333333,
        "category": "platform_specific"
      }
    ],
    "campaign_analysis": [
      {
        "question": "Which campaign performed best?",
        "expected": 3.6734999999999998,
        "category": "campaign_analysis"
      }
    ],
    "advanced_analysis": [
      {
        "question": "What did we learn from this campaign?",
        "expected": "insights",
        "category": "advanced_analysis"
      },
      {
        "question": "How can I optimize my campaigns?",
        "expected": "recommendations",
        "category": "advanced_analysis"
      },
      {
        "question": "What is our campaign summary?",
        "expected": "summary",
        "category": "advanced_analysis"
      }
    ]
  }
}